[
   {
      "img":"https://i.ibb.co/ZVjrSFr/slide-2.png",
     "title": "Discover Love, Adopt Joy",
     "subtitle": "Connecting Hearts, One Paw at a Time."
   },
   {
   "img":"https://i.ibb.co/47fQqsz/slide-1.png",
     "title": "Paws for a Cause",
     "subtitle": "Find Your Furry Companion and Change a Life Forever."
   },
   {
      "img":"https://i.ibb.co/5vk2Tgn/slide-3.png",
     "title": "Embrace Unconditional Love",
     "subtitle": "Where Adorable Pets Await Their Forever Homes."
   },
   {
      "img":"https://i.ibb.co/VvqZBxY/slide-4.jpg",
     "title": "Home is Where the Paw Is",
     "subtitle": "Create Your Happily Ever After with a Furry Friend."
   }
 ]
 